textblob_ar/__init__.py
textblob_ar/blob.py
textblob_ar/correction.py
textblob_ar/pos_tagger.py
textblob_ar/sentiment.py
textblob_ar/similarity.py
textblob_ar/tokenizer.py
textblob_ar/utils.py
textblob_ar_mk-0.0.2.dist-info/DESCRIPTION.rst
textblob_ar_mk-0.0.2.dist-info/METADATA
textblob_ar_mk-0.0.2.dist-info/RECORD
textblob_ar_mk-0.0.2.dist-info/WHEEL
textblob_ar_mk-0.0.2.dist-info/metadata.json
textblob_ar_mk-0.0.2.dist-info/top_level.txt
