Metadata-Version: 2.0
Name: textblob-ar-mk
Version: 0.0.2
Summary: Arabic language extension for TextBlob.
Home-page: https://github.com/adhaamehab/textblob-ar
Author: Adham Ehab, Ibrahim Sharaf
Author-email: adhaamehab7@gmail.com
License: Copyright 2013 Steven Loria
Requires-Dist: textblob (>=0.8.0)
